LICENSE
README.md
setup.py
climetlab_wekeo_source/__init__.py
climetlab_wekeo_source.egg-info/PKG-INFO
climetlab_wekeo_source.egg-info/SOURCES.txt
climetlab_wekeo_source.egg-info/dependency_links.txt
climetlab_wekeo_source.egg-info/entry_points.txt
climetlab_wekeo_source.egg-info/requires.txt
climetlab_wekeo_source.egg-info/top_level.txt
climetlab_wekeo_source.egg-info/zip-safe
climetlab_wekeo_source/tests/__init__.py
climetlab_wekeo_source/tests/test_basic.py